yao_test/__init__.py
yao_test/test001.py
yao_test-0.1.dist-info/METADATA
yao_test-0.1.dist-info/WHEEL
yao_test-0.1.dist-info/top_level.txt
yao_test-0.1.dist-info/RECORD
