Metadata-Version: 2.1
Name: yao_test
Version: 0.1
Summary: one test
Home-page: https://github.com/yourusername/my_package
Author: Yaohoohi
Author-email: yaohoohi@qq.com
License: MIT
Requires-Dist: pandas
